furomon/__init__.py
furomon/_demo_module.py
furomon/navigation.py
furomon/sphinxext.py
furomon/assets/scripts/furomon.js
furomon/assets/scripts/gumshoe-patched.js
furomon/assets/styles/_scaffold.sass
furomon/assets/styles/_shame.sass
furomon/assets/styles/furo-extensions.sass
furomon/assets/styles/furomon.sass
furomon/assets/styles/base/_index.sass
furomon/assets/styles/base/_print.sass
furomon/assets/styles/base/_screen-readers.sass
furomon/assets/styles/base/_theme.sass
furomon/assets/styles/base/_typography.sass
furomon/assets/styles/components/_footer.sass
furomon/assets/styles/components/_index.sass
furomon/assets/styles/components/_search.sass
furomon/assets/styles/components/_sidebar.sass
furomon/assets/styles/components/_table_of_contents.sass
furomon/assets/styles/content/_admonitions.sass
furomon/assets/styles/content/_api.sass
furomon/assets/styles/content/_blocks.sass
furomon/assets/styles/content/_captions.sass
furomon/assets/styles/content/_code.sass
furomon/assets/styles/content/_footnotes.sass
furomon/assets/styles/content/_gui-labels.sass
furomon/assets/styles/content/_images.sass
furomon/assets/styles/content/_index.sass
furomon/assets/styles/content/_indexes.sass
furomon/assets/styles/content/_lists.sass
furomon/assets/styles/content/_math.sass
furomon/assets/styles/content/_misc.sass
furomon/assets/styles/content/_rubrics.sass
furomon/assets/styles/content/_sidebar.sass
furomon/assets/styles/content/_tables.sass
furomon/assets/styles/content/_target.sass
furomon/assets/styles/extensions/_copybutton.sass
furomon/assets/styles/extensions/_index.sass
furomon/assets/styles/extensions/_readthedocs.sass
furomon/assets/styles/extensions/_sphinx-design.sass
furomon/assets/styles/extensions/_sphinx-inline-tabs.sass
furomon/assets/styles/extensions/_sphinx-panels.sass
furomon/assets/styles/variables/_admonitions.scss
furomon/assets/styles/variables/_colors.scss
furomon/assets/styles/variables/_fonts.scss
furomon/assets/styles/variables/_icons.scss
furomon-2022.1.4.dist-info/entry_points.txt
furomon-2022.1.4.dist-info/LICENSE
furomon-2022.1.4.dist-info/WHEEL
furomon-2022.1.4.dist-info/METADATA
furomon-2022.1.4.dist-info/RECORD
