Metadata-Version: 2.1
Name: furomon
Version: 2022.1.4
Summary: A clean customisable Sphinx documentation theme based on furo.
Author-email: Gerrishon Sirere <scalabli@proton.me>
Requires-Python: >=3.7
Classifier: Framework :: Sphinx
Classifier: Framework :: Sphinx :: Theme
Classifier: Development Status :: 5 - Production/Stable
Classifier: License :: OSI Approved :: MIT License
Classifier: Environment :: Web Environment
Classifier: Intended Audience :: Developers
Classifier: Programming Language :: Python :: 3
Classifier: Programming Language :: Python :: 3.5
Classifier: Programming Language :: Python :: 3.6
Classifier: Programming Language :: Python :: 3.7
Classifier: Programming Language :: Python :: 3.8
Classifier: Programming Language :: Python :: 3.9
Classifier: Operating System :: OS Independent
Classifier: Topic :: Documentation
Classifier: Topic :: Software Development :: Documentation
Requires-Dist: beautifulsoup4
Requires-Dist: sphinx >= 4.0,<6.0
Requires-Dist: sphinx-basic-ng
Requires-Dist: pygments >= 2.7
Project-URL: GitHub, https://github.com/scalabli/furomon
